[{"featureShape":[2048],"annotation":"NonIdCard"},{"annotation":"NonIdCard","featureShape":[2048]},{"annotation":"NonIdCard","featureShape":[2048]},{"annotation":"NonIdCard","featureShape":[2048]},{"annotation":"NonIdCard","featureShape":[2048]},{"annotation":"NonIdCard","featureShape":[2048]},{"featureShape":[2048],"annotation":"NonIdCard"},{"annotation":"NonIdCard","featureShape":[2048]},{"featureShape":[2048],"annotation":"NonIdCard"},{"featureShape":[2048],"annotation":"NonIdCard"},{"annotation":"NonIdCard","featureShape":[2048]},{"annotation":"NonIdCard","featureShape":[2048]},{"annotation":"IdCard","featureShape":[2048]},{"featureShape":[2048],"annotation":"IdCard"},{"featureShape":[2048],"annotation":"IdCard"},{"featureShape":[2048],"annotation":"NonIdCard"},{"annotation":"IdCard","featureShape":[2048]},{"featureShape":[2048],"annotation":"NonIdCard"},{"annotation":"IdCard","featureShape":[2048]},{"annotation":"IdCard","featureShape":[2048]},{"featureShape":[2048],"annotation":"IdCard"},{"annotation":"IdCard","featureShape":[2048]},{"featureShape":[2048],"annotation":"IdCard"},{"annotation":"IdCard","featureShape":[2048]},{"featureShape":[2048],"annotation":"IdCard"},{"featureShape":[2048],"annotation":"IdCard"},{"featureShape":[2048],"annotation":"IdCard"},{"annotation":"IdCard","featureShape":[2048]},{"featureShape":[2048],"annotation":"IdCard"},{"annotation":"IdCard","featureShape":[2048]},{"annotation":"IdCard","featureShape":[2048]},{"annotation":"IdCard","featureShape":[2048]},{"featureShape":[2048],"annotation":"IdCard"},{"annotation":"IdCard","featureShape":[2048]},{"featureShape":[2048],"annotation":"IdCard"},{"featureShape":[2048],"annotation":"IdCard"},{"featureShape":[2048],"annotation":"IdCard"},{"annotation":"IdCard","featureShape":[2048]},{"featureShape":[2048],"annotation":"IdCard"},{"annotation":"IdCard","featureShape":[2048]},{"featureShape":[2048],"annotation":"IdCard"},{"annotation":"IdCard","featureShape":[2048]},{"featureShape":[2048],"annotation":"IdCard"},{"annotation":"IdCard","featureShape":[2048]},{"featureShape":[2048],"annotation":"IdCard"},{"annotation":"IdCard","featureShape":[2048]},{"annotation":"IdCard","featureShape":[2048]},{"featureShape":[2048],"annotation":"IdCard"},{"annotation":"IdCard","featureShape":[2048]},{"annotation":"IdCard","featureShape":[2048]},{"featureShape":[2048],"annotation":"IdCard"},{"featureShape":[2048],"annotation":"IdCard"},{"featureShape":[2048],"annotation":"IdCard"},{"annotation":"IdCard","featureShape":[2048]}]